emzed_gui/__init__.py
emzed_gui/_qt_compat.py
emzed_gui/configs.py
emzed_gui/dialog_builder.py
emzed_gui/emzed_dialog.py
emzed_gui/file_dialogs.py
emzed_gui/fix_import_order.py
emzed_gui/helpers.py
emzed_gui/inspect.py
emzed_gui/inspectors.py
emzed_gui/simple_dialogs.py
emzed_gui/optimized/__init__.py
emzed_gui/optimized/optimized.c
emzed_gui/optimized/optimized.cp310-win_amd64.pyd
emzed_gui/optimized/optimized.pyx
emzed_gui/peakmap_explorer/__init__.py
emzed_gui/peakmap_explorer/peakmap_explorer.py
emzed_gui/resources/__init__.py
emzed_gui/resources/icon64.png
emzed_gui/table_explorer/__init__.py
emzed_gui/table_explorer/_debug.py
emzed_gui/table_explorer/_table_explorer_dialog.py
emzed_gui/table_explorer/ask_value.py
emzed_gui/table_explorer/async_runner.py
emzed_gui/table_explorer/button_delegate.py
emzed_gui/table_explorer/image_dialog.py
emzed_gui/table_explorer/inspect.py
emzed_gui/table_explorer/table_explorer.py
emzed_gui/table_explorer/table_explorer_layout.py
emzed_gui/table_explorer/table_explorer_model.py
emzed_gui/table_explorer/table_explorer_model_actions.py
emzed_gui/table_explorer/table_view.py
emzed_gui/table_explorer/text_delegate.py
emzed_gui/widgets/__init__.py
emzed_gui/widgets/_ask_value_dialog.py
emzed_gui/widgets/_choose_range.py
emzed_gui/widgets/_choose_spectra_widget.py
emzed_gui/widgets/_choose_value.py
emzed_gui/widgets/_column_selection_dialog.py
emzed_gui/widgets/_filter_criteria_widget.py
emzed_gui/widgets/_image_scaling_widget.py
emzed_gui/widgets/_integration_widget.py
emzed_gui/widgets/_spectra_selector_widget.py
emzed_gui/widgets/_string_filter.py
emzed_gui/widgets/_view_range_widget.py
emzed_gui/widgets/ask_value_dialogs.py
emzed_gui/widgets/choose_spectra_widget.py
emzed_gui/widgets/column_selection_dialog.py
emzed_gui/widgets/config.py
emzed_gui/widgets/eic_plotting_widget.py
emzed_gui/widgets/filter_criteria_widget.py
emzed_gui/widgets/image_scaling_widget.py
emzed_gui/widgets/integration_widget.py
emzed_gui-3.0.0a25.dist-info/licenses/LICENSE
emzed_gui-3.0.0a25.dist-info/METADATA
emzed_gui-3.0.0a25.dist-info/WHEEL
emzed_gui-3.0.0a25.dist-info/top_level.txt
emzed_gui-3.0.0a25.dist-info/RECORD
