Metadata-Version: 2.4
Name: emzed_gui
Version: 3.0.0a25
Author-email: Uwe Schmitt <uwe.schmitt@id.ethz.ch>
License: MIT
Project-URL: Homepage, https://emzed.ethz.ch
Requires-Python: <3.13,>=3.10
License-File: LICENSE
Requires-Dist: emzed>=3.0.0a22
Requires-Dist: PyQt5
Requires-Dist: PyQt5-Qt5
Requires-Dist: guidata==1.7.7
Requires-Dist: pythonqwt==0.5.5
Requires-Dist: guiqwt303>=3.0.3
Requires-Dist: matplotlib
Requires-Dist: numpy
Dynamic: license-file
